[
  { "path": "dashboard.characters.detail.canonFacts", "value": "設定事實" },
  { "path": "dashboard.characters.emptyBody", "value": "新增你的第一位人物。我們會建立設定條目，並在你寫作時留意一致性。" },
  { "path": "dashboard.inbox.emptyBody", "value": "Seizn 會在你寫作時，把設定、人物與時間軸的衝突彙整到這裡。" },
  { "path": "dashboard.simulate.empty.body", "value": "選兩位人物與一個節拍，我們會依你的設定回放他們的反應 — 落筆前確認很有用。" },
  { "path": "dashboard.timeline.error", "value": "時間軸載入失敗，請重試。" },
  { "path": "dashboard.account.apiKeys.revokeBody", "value": "撤銷「{name}」後，使用此金鑰的呼叫會立即停止，應用程式需要更換新金鑰。" },
  { "path": "dashboard.account.apiKeys.errors.internal", "value": "操作失敗，請稍後再試。" },
  { "path": "dashboard.account.apiKeys.revokeTitle", "value": "撤銷此金鑰？" },
  { "path": "dashboard.account.apiKeys.rotateTitle", "value": "輪換此金鑰？" },
  { "path": "dashboard.account.apiKeys.scopesDefault", "value": "預設權限：recall、remember、graph、search。" },
  { "path": "dashboard.commandPalette.placeholder", "value": "搜尋頁面…" },
  { "path": "dashboard.memoryHealth.syncing", "value": "同步中…" },
  { "path": "dashboard.commandPalette.noResults", "value": "找不到結果" },
  { "path": "dashboard.commandPalette.navigate", "value": "前往" },
  { "path": "dashboard.graph.emptyBody", "value": "新增兩位人物和一段關係，關係圖會在你寫作時自動補上 — 不必手動維護。" },
  { "path": "dashboard.timeline.event.backlogGenerated.label", "value": "產生 Backlog" },
  { "path": "dashboard.timeline.event.backlogGenerated.group", "value": "產生 {count} 次 Backlog" },
  { "path": "dashboard.inbox.filter.reviews", "value": "待審" },
  { "path": "dashboard.nav.review", "value": "審閱" },
  { "path": "dashboard.inbox.detail.suggestion", "value": "建議解法" },
  { "path": "dashboard.fallback.body", "value": "此頁籤沿用相同的版面樣式。" },
  { "path": "dashboard.simulate.hint.help", "value": "如何使用模擬" },
  { "path": "dashboard.timeline.subtitle", "value": "依時間倒序顯示此專案的活動。" },
  { "path": "dashboard.account.apiKeys.audit.description", "value": "記錄 API 金鑰的建立、撤銷、輪換、速率限制、配額與權限事件。" },
  { "path": "dashboard.workspace.switcher.entries", "value": "{count} 個條目" }
]
